lyr/__init__.py
lyr/genius.py
lyr/google.py
lyr-0.0.5.dist-info/METADATA
lyr-0.0.5.dist-info/RECORD
lyr-0.0.5.dist-info/WHEEL
lyr-0.0.5.dist-info/top_level.txt
tests/__init__.py
tests/lyr/__init__.py
tests/lyr/test_genius.py
tests/lyr/test_google.py
